DXJCOMMUNITY/__init__.py
DXJCOMMUNITY/logo.py
dxjcommunity-0.1.0.dist-info/licenses/LICENSE
dxjcommunity-0.1.0.dist-info/METADATA
dxjcommunity-0.1.0.dist-info/WHEEL
dxjcommunity-0.1.0.dist-info/top_level.txt
dxjcommunity-0.1.0.dist-info/RECORD
