Metadata-Version: 2.4
Name: dxjcommunity
Version: 0.1.0
Summary: Modul DROPXJUNGLER untuk menampilkan logo ASCII dan fungsi pendukung lainnya
Home-page: https://github.com/ntfound-dev/modul001
Author: dxjcommunity
Author-email: frendicahyow@gmail.com
Classifier: Programming Language :: Python :: 3
Classifier: License :: OSI Approved :: MIT License
Classifier: Operating System :: OS Independent
Requires-Python: >=3.6
License-File: LICENSE
Dynamic: author
Dynamic: author-email
Dynamic: classifier
Dynamic: description
Dynamic: description-content-type
Dynamic: home-page
Dynamic: license-file
Dynamic: requires-python
Dynamic: summary
